malib/__init__.py
malib/cached_stubs.py
malib/confidence.py
malib/exact_cover.py
malib/pytorch_bivariate_normal.py
malib/pytorch_interp.py
malib/ratelimiter.py
malib/sync_gen.py
malib/ttl_cache.py
malib-0.11.4.dist-info/METADATA
malib-0.11.4.dist-info/WHEEL
malib-0.11.4.dist-info/RECORD
