Metadata-Version: 2.4
Name: malib
Version: 0.11.4
Summary: 
Author: Louis Abraham
Author-email: louis.abraham@yahoo.fr
Requires-Python: >=3.8,<4.0
Classifier: Programming Language :: Python :: 3
Classifier: Programming Language :: Python :: 3.8
Classifier: Programming Language :: Python :: 3.9
Classifier: Programming Language :: Python :: 3.10
Classifier: Programming Language :: Python :: 3.11
Classifier: Programming Language :: Python :: 3.12
Classifier: Programming Language :: Python :: 3.13
Classifier: Programming Language :: Python :: 3.14
Requires-Dist: joblib (>=1.4.2,<2.0.0)
Requires-Dist: nest-asyncio (>=1.6.0,<2.0.0)
Project-URL: Repository, https://github.com/louisabraham/malib
